discord_reargparse/__init__.py
discord_reargparse/argparse.py
discord_reargparse/errors.py
discord_reargparse-0.0.1.dist-info/WHEEL
discord_reargparse-0.0.1.dist-info/METADATA
discord_reargparse-0.0.1.dist-info/RECORD
