Metadata-Version: 2.1
Name: discord-reargparse
Version: 0.0.1
Summary: RegEx based argument parsing for commands in discord.py
Home-page: https://github.com/nkpro2000sr/discord-reargparse
License: MIT
Keywords: discord,regex,argparse,reargparse
Author: nkpro2000sr
Author-email: srnaveen2k@yahoo.com
Maintainer: nkpro2000sr
Maintainer-email: srnaveen2k@yahoo.com
Requires-Python: >=3.6,<4.0
Classifier: License :: OSI Approved :: MIT License
Classifier: Programming Language :: Python :: 3
Classifier: Programming Language :: Python :: 3.6
Classifier: Programming Language :: Python :: 3.7
Classifier: Programming Language :: Python :: 3.8
Requires-Dist: discord.py (>=1.0.0,<2.0.0)
Project-URL: Repository, https://github.com/nkpro2000sr/discord-reargparse
